sonnencharger/__init__.py
sonnencharger/sonnencharger.py
sonnencharger-0.3.0.dist-info/LICENSE
sonnencharger-0.3.0.dist-info/METADATA
sonnencharger-0.3.0.dist-info/WHEEL
sonnencharger-0.3.0.dist-info/top_level.txt
sonnencharger-0.3.0.dist-info/RECORD
