Metadata-Version: 2.1
Name: sonnencharger
Version: 0.3.0
Summary: "SonnenCharger access via ModBus"
Home-page: https://github.com/rustydust/python_sonnencharger
Author: RustyDust
License: GPLv3
Project-URL: Issue Tracker, https://github.com/rustydust/python_sonnencharger/issues
Classifier: Development Status :: 4 - Beta
Classifier: Programming Language :: Python :: 3.8
Classifier: Operating System :: OS Independent
Classifier: Environment :: Console
Classifier: License :: OSI Approved :: GNU General Public License v3 (GPLv3)
Requires-Python: >=3.8
License-File: LICENSE
Requires-Dist: pymodbus>=3.7.0
